{
    "algorithms": [
        {
            "RadiusNeighborsTransformer": {
                "mode": {
                    "value": "distance"
                },
                "radius": {
                    "value": -2.8314378503067967
                },
                "algorithm": {
                    "value": "ball_tree"
                },
                "leaf_size": {
                    "value": 39
                },
                "p": {
                    "value": 1
                }
            }
        },
        {
            "KNeighborsClassifier": {
                "n_neighbors": {
                    "value": 9
                },
                "weights": {
                    "value": "distance"
                },
                "algorithm": {
                    "value": "kd_tree"
                },
                "leaf_size": {
                    "value": 13
                },
                "p": {
                    "value": 1
                },
                "metric": {
                    "value": "l2"
                }
            }
        }
    ],
    "dataset_features": [
        25000.0,
        2.0,
        0.9999999997114609,
        0.5,
        0.5,
        1.0,
        1325.06964,
        1003.1136072002365,
        0.7570270851577556,
        0.75808
    ],
    "system_features": [],
    "dataset_feature_extractor_name": "TextClassificationFeatureExtractor",
    "system_feature_extractor_name": "NoSystem",
    "timestamp": "2025-02-06 04:51:50",
    "alias": "imdb",
    "accuracy": null,
    "cross_val_steps": null,
    "f1": null,
    "evaluation_time": null,
    "error": "Exceeded allowed time for execution. The process was terminated after 60 seconds."
}