{
    "algorithms": [
        {
            "PowerTransformer": {
                "standardize": {
                    "value": false
                }
            }
        },
        {
            "PassiveAggressiveClassifier": {
                "C": {
                    "value": 3.935914794365135
                },
                "fit_intercept": {
                    "value": false
                },
                "tol": {
                    "value": -0.002686634301093124
                },
                "early_stopping": {
                    "value": false
                },
                "validation_fraction": {
                    "value": 0.006
                },
                "n_iter_no_change": {
                    "value": 5
                },
                "shuffle": {
                    "value": true
                },
                "average": {
                    "value": true
                }
            }
        }
    ],
    "dataset_features": [
        2000.0,
        15.0,
        2.836726716298423,
        0.003,
        0.292,
        0.010273972602739727,
        21.1935,
        21.520247622878323,
        1.0154173507385906,
        0.6555
    ],
    "system_features": [],
    "dataset_feature_extractor_name": "TextClassificationFeatureExtractor",
    "system_feature_extractor_name": "NoSystem",
    "timestamp": "2025-02-06 06:02:45",
    "alias": "nps_chat",
    "accuracy": null,
    "cross_val_steps": null,
    "f1": null,
    "evaluation_time": null,
    "error": "module 'numpy' has no attribute 'warnings'"
}